veri_agents_aiware/__init__.py
veri_agents_aiware/utils.py
veri_agents_aiware/aiware_client/async_client.py
veri_agents_aiware/aiware_client/client.py
veri_agents_aiware/aiware_client/graphql/client_generated/__init__.py
veri_agents_aiware/aiware_client/graphql/client_generated/async_client.py
veri_agents_aiware/aiware_client/graphql/client_generated/async_client_ref.py
veri_agents_aiware/aiware_client/graphql/client_generated/base_model_ref.py
veri_agents_aiware/aiware_client/graphql/client_generated/client.py
veri_agents_aiware/aiware_client/graphql/client_generated/client_ref.py
veri_agents_aiware/aiware_client/graphql/client_generated/enums.py
veri_agents_aiware/aiware_client/graphql/client_generated/fragments.py
veri_agents_aiware/aiware_client/graphql/client_generated/input_types.py
veri_agents_aiware/aiware_client/graphql/client_generated/rag_get_td_os_meta.py
veri_agents_aiware/aiware_client/graphql/client_generated/rag_get_tdo_content.py
veri_agents_aiware/aiware_client/graphql/operations/RAG_GetTDO_Content.graphql
veri_agents_aiware/aiware_client/graphql/operations/RAG_GetTDOs_Meta.graphql
veri_agents_aiware/aiware_client/graphql/operations/fragments/TDO_Content.graphql
veri_agents_aiware/aiware_client/graphql/operations/fragments/TDO_Meta.graphql
veri_agents_aiware/api/graphql.py
veri_agents_aiware/knowledgebase/__init__.py
veri_agents_aiware/knowledgebase/knowledgebase.py
veri_agents_aiware/knowledgebase/tools.py
veri_agents_aiware/llm_gateway/__init__.py
veri_agents_aiware/llm_gateway/langchain.py
veri_agents_aiware/tests/aiware_tool_test.py
veri_agents_aiware/tools/__init__.py
veri_agents_aiware/tools/graphql.py
veri_agents_aiware-0.1.9.dist-info/METADATA
veri_agents_aiware-0.1.9.dist-info/WHEEL
veri_agents_aiware-0.1.9.dist-info/RECORD
