Metadata-Version: 2.4
Name: veri-agents-aiware
Version: 0.1.9
Summary: Veritone Agents Toolkit: aiWARE-related tools
Author-email: Markus Toman <mtoman@veritone.com>, Teo Boley <tboley@veritone.com>
Requires-Python: >=3.12
Requires-Dist: veri-agents-common[graphql,langchain-openai]>=0.1.3
Requires-Dist: veri-agents-knowledgebase>=0.1.11
Provides-Extra: all
Provides-Extra: dev
Requires-Dist: aiware>=0.2.5; extra == 'dev'
